kedro_sphinx_theme/__init__.py
kedro_sphinx_theme/assets/scripts/.gitkeep
kedro_sphinx_theme/assets/styles/qb1-sphinx-rtd.css
kedro_sphinx_theme/assets/styles/theme-overrides.css
kedro_sphinx_theme/py.typed
kedro_sphinx_theme/theme/kedro-sphinx-theme/layout.html
kedro_sphinx_theme/theme/kedro-sphinx-theme/static/close-icon.svg
kedro_sphinx_theme/theme/kedro-sphinx-theme/static/kedro-horizontal-color-on-light.svg
kedro_sphinx_theme/theme/kedro-sphinx-theme/static/menu-icon.svg
kedro_sphinx_theme/theme/kedro-sphinx-theme/static/styles/.gitkeep
kedro_sphinx_theme/theme/kedro-sphinx-theme/static/styles/kedro-sphinx-theme.css
kedro_sphinx_theme/theme/kedro-sphinx-theme/theme.conf
kedro_sphinx_theme-2024.10.3.dist-info/LICENSE
kedro_sphinx_theme-2024.10.3.dist-info/METADATA
kedro_sphinx_theme-2024.10.3.dist-info/WHEEL
kedro_sphinx_theme-2024.10.3.dist-info/entry_points.txt
kedro_sphinx_theme-2024.10.3.dist-info/RECORD