Metadata-Version: 2.1
Name: kedro-sphinx-theme
Version: 2024.10.3
Summary: Sphinx theme for the Kedro ecosystem
Author-Email: =?utf-8?q?Juan_Luis_Cano_Rodr=C3=ADguez?= <juan_luis_cano@mckinsey.com>
License:                                  Apache License
Classifier: Development Status :: 3 - Alpha
Classifier: Intended Audience :: Developers
Classifier: License :: OSI Approved :: Apache Software License
Classifier: Operating System :: OS Independent
Classifier: Programming Language :: Python
Classifier: Programming Language :: Python :: 3
Classifier: Programming Language :: Python :: 3.8
Classifier: Programming Language :: Python :: 3.9
Classifier: Programming Language :: Python :: 3.10
Classifier: Programming Language :: Python :: 3.11
Classifier: Programming Language :: Python :: 3.12
Classifier: Framework :: Sphinx
Classifier: Framework :: Sphinx :: Theme
Project-URL: source, https://github.com/kedro-org/kedro-sphinx-theme
Project-URL: tracker, https://github.com/kedro-org/kedro-sphinx-theme/issues
Project-URL: documentation, https://kedro-sphinx-theme.readthedocs.io
Requires-Python: >=3.8
Requires-Dist: docutils<0.21
Requires-Dist: sphinx<7.3,>=5.3
Requires-Dist: sphinx_rtd_theme==2.0.0
Requires-Dist: sphinx-autodoc-typehints==1.20.2
Requires-Dist: sphinx_copybutton==0.5.2
Requires-Dist: sphinx-notfound-page
Requires-Dist: myst-parser<2.1,>=1.0
Requires-Dist: sphinx-last-updated-by-git
Requires-Dist: sphinx-favicon
Requires-Dist: sphinxcontrib-youtube
Provides-Extra: test
Requires-Dist: mypy; extra == "test"
Requires-Dist: hypothesis; extra == "test"
Requires-Dist: pytest; extra == "test"
Requires-Dist: pytest-cov; extra == "test"
Provides-Extra: doc
Requires-Dist: kedro-sphinx-theme; extra == "doc"
